armorstand/__init__.py
armorstand/date/__init__.py
armorstand/date/date.py
armorstand/date/test_date.py
armorstand/youtube/__init__.py
armorstand/youtube/download.py
armorstand/youtube/test_video_id.py
armorstand/youtube/video_id.py
armorstand-21.2.22.20.27.dist-info/WHEEL
armorstand-21.2.22.20.27.dist-info/METADATA
armorstand-21.2.22.20.27.dist-info/RECORD
